{"serialpos": [[1, 18, 17, 13, -999, -999, -999, 0, 0], [18, 14, 16, 13, 12, 2, 4, 10, 0], [20, 19, 24, 6, 8, 3, 17, -999, 0], [6, 5, 8, 9, 10, -999, 0, 0, 0], [9, 10, 12, 5, 6, 0, 0, 0, 0], [5, 4, 6, 23, 24, 19, 17, -999, 16], [5, 6, 9, 11, 0, 0, 0, 0, 0], [10, 12, 11, 9, 6, 0, 0, 0, 0], [10, 11, 12, 6, 7, 0, 0, 0, 0], [20, 21, 22, 24, 7, 5, 16, 0, 0], [24, 21, 20, 16, 5, 2, 0, 0, 0], [21, 22, 16, 4, 3, 8, 0, 0, 0], [4, 5, 21, 22, 20, 10, 8, -999, 0], [4, 5, 6, 8, 10, 11, 12, 0, 0], [8, 9, 10, 11, 7, 12, 0, 0, 0], [6, 8, 9, 10, 11, 0, 0, 0, 0], [21, 23, 24, 9, 14, 7, 6, 0, 0], [24, 18, 5, 8, 6, 11, 9, 8, -15]], "ffr_serialpos": [24, 18, 6, 9, 3, 11, 5, 10, 20, 2, 1, 8, 7, 6, 11, 9, 17, -999], "ffr_pres_trial": [17, 17, 3, 17, 17, 2, 17, 1, 2, 17, 17, 17, 15, 17, 17, 11, 0, -999], "rec_words": [["xerox", "snack", "pigeon", "gavel", "apple", "bird", "capital", 0, 0], ["saddle", "cigar", "rooster", "glove", "robber", "proton", "skirt", "boyfriend", 0], ["daughter", "girl", "suitcase", "permit", "stone", "sibling", "tart", "friend", 0], ["icing", "peanut", "tutu", "juggler", "shelf", "cake", 0, 0, 0], ["denim", "uncle", "shovel", "twig", "lion", 0, 0, 0, 0], ["mammal", "shark", "silk", "mailman", "snail", "monster", "casket", "cade", "cafe"], ["grape", "bison", "donkey", "poet", 0, 0, 0, 0, 0], ["wrist", "county", "cyclone", "cabbage", "woman", 0, 0, 0, 0], ["bullet", "lizard", "pluto", "knife", "plaster", 0, 0, 0, 0], ["clam", "hawk", "honey", "atom", "carrot", "crevice", "plaid", 0, 0], ["hound", "tombstone", "fungus", "kidney", "chemist", "ozone", 0, 0, 0], ["onion", "radish", "perfume", "blender", "mars", "turtle", 0, 0, 0], ["river", "rattle", "muffin", "playground", "pliers", "actor", "infant", "sly", 0], ["heart", "plate", "candy", "london", "lace", "velvet", "baby", 0, 0], ["sticker", "receipt", "supper", "lunch", "mailbox", "window", 0, 0, 0], ["stamp", "knapsack", "patient", "treat", "drink", 0, 0, 0, 0], ["breast", "beef", "garbage", "shorts", "brandy", "cashier", "bank", 0, 0], ["fox", "outdoors", "lady", "jello", "bucket", "basement", "fruit", "jello", "robot"]], "ffr_rec_words": ["fox", "outdoors", "icing", "fruit", "pizza", "robot", "lady", "boyfriend", "daughter", "outfit", "peach", "jello", "dress", "bucket", "basement", "dolphin", "pigeon", "bird"], "pres_words": [["xerox", "shirt", "bug", "goblin", "popcorn", "female", "mask", "daisy", "fireplace", "parent", "mattress", "relish", "gavel", "ointment", "star", "forest", "pigeon", "snack", 0, 0, 0, 0, 0, 0], ["mummy", "proton", "sparrow", "skirt", "canyon", "powder", "lily", "skillet", "napkin", "boyfriend", "notebook", "robber", "glove", "cigar", "student", "rooster", "brother", "saddle", 0, 0, 0, 0, 0, 0], ["japan", "husband", "sibling", "waitress", "novel", "permit", "brick", "stone", "hostess", "contract", "robot", "kleenex", "maple", "panther", "swimmer", "victim", "tart", "pebble", "girl", "daughter", "bubble", "zebra", "tablet", "suitcase"], ["lagoon", "umpire", "servant", "marsh", "peanut", "icing", "wardrobe", "tutu", "juggler", "shelf", "pastry", "sandwich", 0, 0, 0, 0, 0, 0, 0, 0, 0, 0, 0, 0], ["dresser", "cupboard", "iceberg", "friend", "twig", "lion", "banjo", "label", "denim", "uncle", "picnic", "shovel", 0, 0, 0, 0, 0, 0, 0, 0, 0, 0, 0, 0], ["blackboard", "valley", "wife", "shark", "mammal", "silk", "compass", "custard", "bouquet", "sister", "padding", "spouse", "crab", "truck", "diner", "cafe", "casket", "sidewalk", "monster", "vagrant", "summit", "seafood", "mailman", "snail"], ["rocket", "missile", "forehead", "blockade", "grape", "bison", "orange", "chipmunk", "donkey", "cattle", "poet", "rabbit", 0, 0, 0, 0, 0, 0, 0, 0, 0, 0, 0, 0], ["convict", "finger", "waiter", "foot", "trench", "woman", "highway", "parsley", "cabbage", "wrist", "cyclone", "county", 0, 0, 0, 0, 0, 0, 0, 0, 0, 0, 0, 0], ["film", "globe", "flower", "lava", "blade", "knife", "plaster", "portrait", "crater", "bullet", "lizard", "pluto", 0, 0, 0, 0, 0, 0, 0, 0, 0, 0, 0, 0], ["cobra", "fiddle", "item", "climber", "crevice", "snake", "carrot", "omelet", "dancer", "grill", "lake", "canal", "patrol", "police", "viking", "plaid", "oyster", "staple", "parrot", "clam", "hawk", "honey", "jelly", "atom"], ["hand", "ozone", "trombone", "chauffeur", "chemist", "bathtub", "wasp", "spider", "smog", "airport", "diver", "lover", "mildew", "ghetto", "milk", "kidney", "pecan", "crayon", "fleet", "fungus", "tombstone", "statue", "wagon", "hound"], ["costume", "queen", "mars", "blender", "razor", "belly", "zipper", "turtle", "dolphin", "scissors", "citrus", "flesh", "plaza", "lettuce", "poison", "perfume", "butcher", "partner", "turkey", "bureau", "onion", "radish", "quail", "banquet"], ["slide", "thread", "egypt", "river", "rattle", "sausage", "pasta", "infant", "widow", "actor", "europe", "rust", "tweezers", "gallon", "machine", "bike", "grave", "creature", "jury", "pliers", "muffin", "playground", "arm", "leg"], ["liver", "pigment", "soda", "heart", "plate", "candy", "mop", "london", "garden", "lace", "velvet", "baby", 0, 0, 0, 0, 0, 0, 0, 0, 0, 0, 0, 0], ["headband", "badge", "hedge", "seal", "beaver", "pimple", "mailbox", "sticker", "receipt", "supper", "lunch", "window", 0, 0, 0, 0, 0, 0, 0, 0, 0, 0, 0, 0], ["lapel", "piston", "valve", "nurse", "body", "stamp", "dress", "knapsack", "patient", "treat", "drink", "child", 0, 0, 0, 0, 0, 0, 0, 0, 0, 0, 0, 0], ["scallop", "bacon", "pork", "orchid", "dandruff", "bank", "cashier", "barrel", "shorts", "pepper", "salmon", "eyelash", "scotch", "brandy", "shoulder", "report", "worker", "ankle", "box", "judge", "breast", "ulcer", "beef", "garbage"], ["peach", "outfit", "pizza", "doughnut", "lady", "bucket", "robin", "jello", "fruit", "perch", "basement", "taxi", "office", "nightgown", "clothes", "possum", "lightning", "outdoors", "cashew", "flute", "scarecrow", "princess", "cloud", "fox"]], "list_len": [18, 18, 24, 12, 12, 24, 12, 12, 12, 24, 24, 24, 24, 12, 12, 12, 24, 24], "pres_rate": [1200, 1200, 800, 800, 800, 800, 1600, 1600, 800, 1600, 800, 1600, 1600, 1600, 1600, 800, 800, 1600], "pres_mod": ["v", "a", "a", "v", "a", "v", "a", "v", "v", "v", "a", "v", "a", "v", "a", "a", "v", "a"], "dist_dur": [18000, 18000, 24000, 12000, 24000, 12000, 24000, 24000, 24000, 24000, 12000, 12000, 12000, 12000, 12000, 12000, 24000, 24000], "math_correct": [[true, true, true, true, true, false, false, false, false, false], [true, true, true, true, true, true, false, false, false, false], [true, false, true, true, true, true, true, true, true, true], [true, true, true, false, false, false, false, false, false, false], [true, false, true, true, true, true, true, true, true, true], [true, true, true, false, false, false, false, false, false, false], [true, true, true, true, true, true, false, true, true, false], [true, true, true, true, true, true, false, true, false, false], [true, true, true, true, true, false, true, true, false, false], [true, true, true, true, true, true, true, true, true, false], [true, true, true, true, false, false, false, false, false, false], [true, true, true, true, false, false, false, false, false, false], [true, true, true, true, false, false, false, false, false, false], [true, true, true, false, false, false, false, false, false, false], [true, true, true, false, false, false, false, false, false, false], [true, true, true, true, false, false, false, false, false, false], [true, true, false, false, true, true, true, true, false, false], [true, true, false, true, true, true, true, false, false, false]], "rt": [[4332, 5829, 7821, 9949, 15405, 24149, 28709, 0, 0], [3181, 5282, 7348, 9298, 10565, 12053, 13732, 15980, 0], [5937, 7519, 10351, 12105, 13235, 16618, 18490, 45852, 0], [3824, 6128, 8176, 11475, 12392, 16960, 0, 0, 0], [5051, 6484, 8420, 11432, 13330, 0, 0, 0, 0], [2734, 3902, 5070, 7686, 9062, 10670, 12406, 13485, 16061], [4196, 6158, 9545, 10996, 0, 0, 0, 0, 0], [4142, 5553, 11524, 13609, 15041, 0, 0, 0, 0], [5285, 7333, 8926, 10630, 12175, 0, 0, 0, 0], [6173, 13384, 18250, 22251, 27613, 34851, 54351, 0, 0], [4794, 7924, 12213, 20381, 23893, 30430, 0, 0, 0], [6391, 9359, 12525, 15297, 17664, 19567, 0, 0, 0], [6793, 8246, 10781, 13695, 17148, 20664, 22499, 43393, 0], [8588, 10470, 14037, 17521, 19573, 21988, 23302, 0, 0], [4784, 7482, 9585, 11298, 13950, 15515, 0, 0, 0], [19393, 22110, 24374, 26759, 28614, 0, 0, 0, 0], [7919, 10352, 13253, 17151, 18834, 26886, 27897, 0, 0], [4470, 6537, 8298, 9802, 14275, 16436, 17690, 19632, 24932]], "recalled": [[1.0, 0.0, 0.0, 0.0, 0.0, 0.0, 0.0, 0.0, 0.0, 0.0, 0.0, 0.0, 1.0, 0.0, 0.0, 0.0, 1.0, 1.0, NaN, NaN, NaN, NaN, NaN, NaN], [0.0, 1.0, 0.0, 1.0, 0.0, 0.0, 0.0, 0.0, 0.0, 1.0, 0.0, 1.0, 1.0, 1.0, 0.0, 1.0, 0.0, 1.0, NaN, NaN, NaN, NaN, NaN, NaN], [0.0, 0.0, 1.0, 0.0, 0.0, 1.0, 0.0, 1.0, 0.0, 0.0, 1.0, 0.0, 0.0, 0.0, 0.0, 0.0, 1.0, 0.0, 1.0, 1.0, 0.0, 0.0, 0.0, 1.0], [0.0, 0.0, 0.0, 0.0, 1.0, 1.0, 0.0, 1.0, 1.0, 1.0, 0.0, 0.0, NaN, NaN, NaN, NaN, NaN, NaN, NaN, NaN, NaN, NaN, NaN, NaN], [0.0, 0.0, 0.0, 0.0, 1.0, 1.0, 0.0, 0.0, 1.0, 1.0, 0.0, 1.0, NaN, NaN, NaN, NaN, NaN, NaN, NaN, NaN, NaN, NaN, NaN, NaN], [0.0, 0.0, 0.0, 1.0, 1.0, 1.0, 0.0, 0.0, 0.0, 0.0, 0.0, 0.0, 0.0, 0.0, 0.0, 1.0, 1.0, 0.0, 1.0, 0.0, 0.0, 0.0, 1.0, 1.0], [0.0, 0.0, 0.0, 0.0, 1.0, 1.0, 0.0, 0.0, 1.0, 0.0, 1.0, 0.0, NaN, NaN, NaN, NaN, NaN, NaN, NaN, NaN, NaN, NaN, NaN, NaN], [0.0, 0.0, 0.0, 0.0, 0.0, 1.0, 0.0, 0.0, 1.0, 1.0, 1.0, 1.0, NaN, NaN, NaN, NaN, NaN, NaN, NaN, NaN, NaN, NaN, NaN, NaN], [0.0, 0.0, 0.0, 0.0, 0.0, 1.0, 1.0, 0.0, 0.0, 1.0, 1.0, 1.0, NaN, NaN, NaN, NaN, NaN, NaN, NaN, NaN, NaN, NaN, NaN, NaN], [0.0, 0.0, 0.0, 0.0, 1.0, 0.0, 1.0, 0.0, 0.0, 0.0, 0.0, 0.0, 0.0, 0.0, 0.0, 1.0, 0.0, 0.0, 0.0, 1.0, 1.0, 1.0, 0.0, 1.0], [0.0, 1.0, 0.0, 0.0, 1.0, 0.0, 0.0, 0.0, 0.0, 0.0, 0.0, 0.0, 0.0, 0.0, 0.0, 1.0, 0.0, 0.0, 0.0, 1.0, 1.0, 0.0, 0.0, 1.0], [0.0, 0.0, 1.0, 1.0, 0.0, 0.0, 0.0, 1.0, 0.0, 0.0, 0.0, 0.0, 0.0, 0.0, 0.0, 1.0, 0.0, 0.0, 0.0, 0.0, 1.0, 1.0, 0.0, 0.0], [0.0, 0.0, 0.0, 1.0, 1.0, 0.0, 0.0, 1.0, 0.0, 1.0, 0.0, 0.0, 0.0, 0.0, 0.0, 0.0, 0.0, 0.0, 0.0, 1.0, 1.0, 1.0, 0.0, 0.0], [0.0, 0.0, 0.0, 1.0, 1.0, 1.0, 0.0, 1.0, 0.0, 1.0, 1.0, 1.0, NaN, NaN, NaN, NaN, NaN, NaN, NaN, NaN, NaN, NaN, NaN, NaN], [0.0, 0.0, 0.0, 0.0, 0.0, 0.0, 1.0, 1.0, 1.0, 1.0, 1.0, 1.0, NaN, NaN, NaN, NaN, NaN, NaN, NaN, NaN, NaN, NaN, NaN, NaN], [0.0, 0.0, 0.0, 0.0, 0.0, 1.0, 0.0, 1.0, 1.0, 1.0, 1.0, 0.0, NaN, NaN, NaN, NaN, NaN, NaN, NaN, NaN, NaN, NaN, NaN, NaN], [0.0, 0.0, 0.0, 0.0, 0.0, 1.0, 1.0, 0.0, 1.0, 0.0, 0.0, 0.0, 0.0, 1.0, 0.0, 0.0, 0.0, 0.0, 0.0, 0.0, 1.0, 0.0, 1.0, 1.0], [0.0, 0.0, 0.0, 0.0, 1.0, 1.0, 0.0, 1.0, 1.0, 0.0, 1.0, 0.0, 0.0, 0.0, 0.0, 0.0, 0.0, 1.0, 0.0, 0.0, 0.0, 0.0, 0.0, 1.0]], "ffr_recalled": [[0.0, 0.0, 0.0, 0.0, 0.0, 0.0, 0.0, 0.0, 0.0, 0.0, 0.0, 0.0, 0.0, 0.0, 0.0, 0.0, 1.0, 0.0, NaN, NaN, NaN, NaN, NaN, NaN], [0.0, 0.0, 0.0, 0.0, 0.0, 0.0, 0.0, 0.0, 0.0, 1.0, 0.0, 0.0, 0.0, 0.0, 0.0, 0.0, 0.0, 0.0, NaN, NaN, NaN, NaN, NaN, NaN], [0.0, 0.0, 0.0, 0.0, 0.0, 0.0, 0.0, 0.0, 0.0, 0.0, 1.0, 0.0, 0.0, 0.0, 0.0, 0.0, 0.0, 0.0, 0.0, 1.0, 0.0, 0.0, 0.0, 0.0], [0.0, 0.0, 0.0, 0.0, 0.0, 1.0, 0.0, 0.0, 0.0, 0.0, 0.0, 0.0, NaN, NaN, NaN, NaN, NaN, NaN, NaN, NaN, NaN, NaN, NaN, NaN], [0.0, 0.0, 0.0, 0.0, 0.0, 0.0, 0.0, 0.0, 0.0, 0.0, 0.0, 0.0, NaN, NaN, NaN, NaN, NaN, NaN, NaN, NaN, NaN, NaN, NaN, NaN], [0.0, 0.0, 0.0, 0.0, 0.0, 0.0, 0.0, 0.0, 0.0, 0.0, 0.0, 0.0, 0.0, 0.0, 0.0, 0.0, 0.0, 0.0, 0.0, 0.0, 0.0, 0.0, 0.0, 0.0], [0.0, 0.0, 0.0, 0.0, 0.0, 0.0, 0.0, 0.0, 0.0, 0.0, 0.0, 0.0, NaN, NaN, NaN, NaN, NaN, NaN, NaN, NaN, NaN, NaN, NaN, NaN], [0.0, 0.0, 0.0, 0.0, 0.0, 0.0, 0.0, 0.0, 0.0, 0.0, 0.0, 0.0, NaN, NaN, NaN, NaN, NaN, NaN, NaN, NaN, NaN, NaN, NaN, NaN], [0.0, 0.0, 0.0, 0.0, 0.0, 0.0, 0.0, 0.0, 0.0, 0.0, 0.0, 0.0, NaN, NaN, NaN, NaN, NaN, NaN, NaN, NaN, NaN, NaN, NaN, NaN], [0.0, 0.0, 0.0, 0.0, 0.0, 0.0, 0.0, 0.0, 0.0, 0.0, 0.0, 0.0, 0.0, 0.0, 0.0, 0.0, 0.0, 0.0, 0.0, 0.0, 0.0, 0.0, 0.0, 0.0], [0.0, 0.0, 0.0, 0.0, 0.0, 0.0, 0.0, 0.0, 0.0, 0.0, 0.0, 0.0, 0.0, 0.0, 0.0, 0.0, 0.0, 0.0, 0.0, 0.0, 0.0, 0.0, 0.0, 0.0], [0.0, 0.0, 0.0, 0.0, 0.0, 0.0, 0.0, 0.0, 1.0, 0.0, 0.0, 0.0, 0.0, 0.0, 0.0, 0.0, 0.0, 0.0, 0.0, 0.0, 0.0, 0.0, 0.0, 0.0], [0.0, 0.0, 0.0, 0.0, 0.0, 0.0, 0.0, 0.0, 0.0, 0.0, 0.0, 0.0, 0.0, 0.0, 0.0, 0.0, 0.0, 0.0, 0.0, 0.0, 0.0, 0.0, 0.0, 0.0], [0.0, 0.0, 0.0, 0.0, 0.0, 0.0, 0.0, 0.0, 0.0, 0.0, 0.0, 0.0, NaN, NaN, NaN, NaN, NaN, NaN, NaN, NaN, NaN, NaN, NaN, NaN], [0.0, 0.0, 0.0, 0.0, 0.0, 0.0, 0.0, 0.0, 0.0, 0.0, 0.0, 0.0, NaN, NaN, NaN, NaN, NaN, NaN, NaN, NaN, NaN, NaN, NaN, NaN], [0.0, 0.0, 0.0, 0.0, 0.0, 0.0, 1.0, 0.0, 0.0, 0.0, 0.0, 0.0, NaN, NaN, NaN, NaN, NaN, NaN, NaN, NaN, NaN, NaN, NaN, NaN], [0.0, 0.0, 0.0, 0.0, 0.0, 0.0, 0.0, 0.0, 0.0, 0.0, 0.0, 0.0, 0.0, 0.0, 0.0, 0.0, 0.0, 0.0, 0.0, 0.0, 0.0, 0.0, 0.0, 0.0], [1.0, 1.0, 1.0, 0.0, 1.0, 1.0, 0.0, 1.0, 1.0, 0.0, 1.0, 0.0, 0.0, 0.0, 0.0, 0.0, 0.0, 1.0, 0.0, 0.0, 0.0, 0.0, 0.0, 1.0]], "ffr_rt": [4049, 10523, 13949, 15170, 17200, 18971, 21738, 23556, 27503, 36683, 42099, 43789, 86281, 137583, 140071, 206947, 210347, 213011], "subject": ["MTK0640", "MTK0640", "MTK0640", "MTK0640", "MTK0640", "MTK0640", "MTK0640", "MTK0640", "MTK0640", "MTK0640", "MTK0640", "MTK0640", "MTK0640", "MTK0640", "MTK0640", "MTK0640", "MTK0640", "MTK0640"], "intrusions": [[0, 0, 0, 0, -1, -1, -1, 0, 0], [0, 0, 0, 0, 0, 0, 0, 0, 0], [0, 0, 0, 0, 0, 0, 0, -1, 0], [0, 0, 0, 0, 0, -1, 0, 0, 0], [0, 0, 0, 0, 0, 0, 0, 0, 0], [0, 0, 0, 0, 0, 0, 0, -1, 0], [0, 0, 0, 0, 0, 0, 0, 0, 0], [0, 0, 0, 0, 0, 0, 0, 0, 0], [0, 0, 0, 0, 0, 0, 0, 0, 0], [0, 0, 0, 0, 0, 0, 0, 0, 0], [0, 0, 0, 0, 0, 0, 0, 0, 0], [0, 0, 0, 0, 0, 0, 0, 0, 0], [0, 0, 0, 0, 0, 0, 0, -1, 0], [0, 0, 0, 0, 0, 0, 0, 0, 0], [0, 0, 0, 0, 0, 0, 0, 0, 0], [0, 0, 0, 0, 0, 0, 0, 0, 0], [0, 0, 0, 0, 0, 0, 0, 0, 0], [0, 0, 0, 0, 0, 0, 0, 0, 15]]}