{"serialpos": [[1, 11, 7, -999, 0, 0, 0, 0, 0, 0, 0, 0, 0, 0], [18, 1, 3, 12, 16, 11, 3, 13, 6, 0, 0, 0, 0, 0], [12, 9, 5, -999, 7, 6, -999, 4, -1, 0, 0, 0, 0, 0], [24, 23, 4, -999, 7, 1, 2, 6, 0, 0, 0, 0, 0, 0], [1, 2, 3, 7, 17, 21, 5, 18, -1, 0, 0, 0, 0, 0], [11, 24, 1, 4, 2, 8, 5, 6, 7, 19, 18, 21, 16, 13], [11, 12, 7, 6, 9, 1, 8, 10, 4, 5, 2, 0, 0, 0], [24, 10, 17, 23, 16, 13, 14, 4, 5, 6, 2, -999, 0, 0], [22, 6, 1, 5, 4, 8, 17, 13, 19, 21, 20, 0, 0, 0], [11, 1, 12, 5, 6, 0, 0, 0, 0, 0, 0, 0, 0, 0], [23, 24, 1, 2, 13, 14, 4, 3, 7, 0, 0, 0, 0, 0], [1, 2, 5, 12, 7, 2, 0, 0, 0, 0, 0, 0, 0, 0], [23, 24, 1, 2, 6, 8, 10, 20, 11, 7, 20, 12, 0, 0], [10, 11, 3, 12, -1, 0, 0, 0, 0, 0, 0, 0, 0, 0], [1, 3, 2, -11, 23, 13, 6, 10, -6, -6, 12, 15, 0, 0], [7, 6, 5, 11, 12, 0, 0, 0, 0, 0, 0, 0, 0, 0], [1, 11, 12, 11, 0, 0, 0, 0, 0, 0, 0, 0, 0, 0], [-11, 11, 12, 9, 0, 0, 0, 0, 0, 0, 0, 0, 0, 0]], "ffr_serialpos": [12, 1, 9, 11, 1, 13, 14, 4, 1, 4, 5, 4, 13, 13, 14, 12, 19, 10, 9, 1, 8, 7, 1, 2, 6, 5, 9, 8, 7, 11, 2, 15, 14, 10, 11, 12, 6, 7, 6, -999, 3, 7, 2, 11, -999, 5, 6, 8, 16], "ffr_pres_trial": [12, 15, 5, 12, 5, 7, 7, 8, 8, 7, 6, 5, 5, 10, 10, 7, 5, 6, 6, 6, 6, 11, 12, 12, 12, 17, 8, 9, 12, 6, 6, 5, 12, 17, 17, 17, 9, 9, 1, -999, 10, 10, 7, 1, -999, 9, 9, 8, 7], "rec_words": [["teacher", "sphinx", "pliers", "clown", 0, 0, 0, 0, 0, 0, 0, 0, 0, 0], ["victim", "salad", "hand", "mustard", "wasp", "sheriff", "hand", "puppy", "bison", 0, 0, 0, 0, 0], ["drill", "daughter", "asia", "costal", "college", "casket", "slant", "japan", "mustard", 0, 0, 0, 0, 0], ["ketchup", "airplane", "lady", "dine", "diner", "necklace", "scallop", "waiter", 0, 0, 0, 0, 0, 0], ["cook", "bunny", "lion", "kitchen", "oyster", "scissors", "knife", "freckle", "ketchup", 0, 0, 0, 0, 0], ["pizza", "sausage", "leg", "fireplace", "silk", "scarf", "perfume", "fragrance", "citrus", "portrait", "boyfriend", "nurse", "bouquet", "office"], ["cloud", "island", "mattress", "gallon", "ox", "cobra", "snake", "egypt", "turtle", "panther", "airport", 0, 0, 0], ["shrub", "hedge", "france", "europe", "crevice", "brother", "sibling", "spouse", "milk", "honey", "thief", "bugler", 0, 0], ["wife", "widow", "preacher", "husband", "uncle", "globe", "atlas", "venus", "garden", "cabbage", "garlic", 0, 0, 0], ["tuba", "trombone", "freezer", "grape", "lunch", 0, 0, 0, 0, 0, 0, 0, 0, 0], ["palace", "chapel", "crab", "cod", "dolphin", "penguin", "arm", "blouse", "skirt", 0, 0, 0, 0, 0], ["grill", "doughnut", "robin", "dust", "peach", "doughnut", 0, 0, 0, 0, 0, 0, 0, 0], ["candy", "river", "scotch", "brandy", "barrel", "turkey", "belly", "body", "wardrobe", "stone", "body", "finger", 0, 0], ["cattle", "machine", "beef", "spider", "candy", 0, 0, 0, 0, 0, 0, 0, 0, 0], ["nomad", "girl", "space", "waiter", "hostess", "actor", "eyelash", "goblin", "monster", "monster", "woman", "lettuce", 0, 0], ["bacon", "mummy", "nightgown", "mailman", "mailbox", 0, 0, 0, 0, 0, 0, 0, 0, 0], ["elbow", "wagon", "custard", "wagon", 0, 0, 0, 0, 0, 0, 0, 0, 0, 0], ["gallon", "lagoon", "rocket", "tractor", 0, 0, 0, 0, 0, 0, 0, 0, 0, 0]], "ffr_rec_words": ["finger", "chest", "breast", "wardrobe", "leg", "brother", "sibling", "uncle", "preacher", "spouse", "panther", "fireplace", "office", "dolphin", "penguin", "glove", "portrait", "egypt", "ox", "cobra", "snake", "peach", "scotch", "brandy", "barrel", "camel", "army", "marine", "stone", "cloud", "airport", "friend", "marsh", "balloon", "lagoon", "rocket", "lunch", "supper", "bison", "jaguar", "blouse", "skirt", "thief", "sheriff", "bandit", "grape", "lunch", "globe", "crevice"], "pres_words": [["teacher", "motel", "worker", "soda", "chemist", "sculpture", "pliers", "jelly", "flute", "notebook", "sphinx", "flashlight", "flesh", "plaid", "perch", "snack", "catcher", "crown", 0, 0, 0, 0, 0, 0], ["salad", "napkin", "hand", "star", "slide", "bison", "staple", "luggage", "termite", "tart", "sheriff", "mustard", "puppy", "kidney", "cocoon", "wasp", "receipt", "victim", 0, 0, 0, 0, 0, 0], ["relish", "tombstone", "slope", "japan", "asia", "casket", "college", "clothes", "daughter", "piano", "stream", "drill", 0, 0, 0, 0, 0, 0, 0, 0, 0, 0, 0, 0], ["necklace", "scallop", "omelet", "lady", "suspect", "waiter", "diner", "dashboard", "brook", "bank", "apron", "handbag", "canyon", "blackboard", "dress", "gift", "champagne", "fruit", "powder", "sunrise", "sunset", "denim", "airplane", "ketchup"], ["cook", "bunny", "lion", "playground", "knife", "sword", "kitchen", "jury", "parent", "outfit", "flask", "coffee", "sticker", "smog", "juggler", "salmon", "oyster", "freckle", "lizard", "badge", "scissors", "lily", "scribble", "tile"], ["leg", "silk", "tortoise", "fireplace", "perfume", "fragrance", "citrus", "scarf", "breast", "fungus", "pizza", "stove", "office", "seal", "friend", "bouquet", "fleet", "boyfriend", "portrait", "hero", "nurse", "patient", "bureau", "sausage"], ["cobra", "airport", "transplant", "turtle", "panther", "gallon", "mattress", "snake", "ox", "egypt", "cloud", "island", 0, 0, 0, 0, 0, 0, 0, 0, 0, 0, 0, 0], ["guitar", "thief", "daisy", "spouse", "milk", "honey", "burglar", "drawing", "ulcer", "hedge", "rod", "glove", "brother", "sibling", "backbone", "crevice", "france", "valve", "tweezers", "subway", "climber", "marker", "europe", "shrub"], ["preacher", "hiker", "pastry", "uncle", "husband", "widow", "kleenex", "globe", "army", "monster", "picnic", "world", "venus", "turnip", "scalpel", "helmet", "atlas", "quail", "garden", "garlic", "cabbage", "wife", "cousin", "dancer"], ["trombone", "harp", "toaster", "cowboy", "grape", "lunch", "supper", "marine", "snail", "shelter", "tuba", "freezer", 0, 0, 0, 0, 0, 0, 0, 0, 0, 0, 0, 0], ["crab", "cod", "blouse", "arm", "vagrant", "mammal", "skirt", "eagle", "bathtub", "donkey", "expert", "velvet", "dolphin", "penguin", "pigeon", "dustpan", "poet", "twig", "cafe", "pepper", "rabbit", "novel", "palace", "chapel"], ["grill", "doughnut", "bike", "pecan", "robin", "fox", "peach", "bug", "spoon", "ghetto", "market", "dust", 0, 0, 0, 0, 0, 0, 0, 0, 0, 0, 0, 0], ["scotch", "brandy", "county", "brick", "flower", "barrel", "stone", "turkey", "shoulder", "belly", "wardrobe", "finger", "dorm", "marsh", "washer", "seafood", "pork", "cookbook", "cashier", "body", "empire", "treat", "candy", "river"], ["captive", "sidewalk", "beef", "dandruff", "apple", "marrow", "liver", "swimmer", "swamp", "cattle", "machine", "spider", 0, 0, 0, 0, 0, 0, 0, 0, 0, 0, 0, 0], ["nomad", "space", "girl", "beast", "critic", "eyelash", "inmate", "tablet", "xerox", "goblin", "dragon", "woman", "actor", "film", "lettuce", "pimple", "bubble", "waitress", "beaker", "heart", "drink", "journal", "hostess", "flag"], ["chest", "lumber", "child", "dresser", "nightgown", "mummy", "bacon", "basement", "report", "stomach", "mailman", "mailbox", 0, 0, 0, 0, 0, 0, 0, 0, 0, 0, 0, 0], ["elbow", "ankle", "blender", "seagull", "muffin", "onion", "icing", "crayon", "match", "yarn", "wagon", "custard", 0, 0, 0, 0, 0, 0, 0, 0, 0, 0, 0, 0], ["crutch", "banjo", "paddle", "missile", "camel", "barley", "canal", "truck", "tractor", "balloon", "lagoon", "rocket", 0, 0, 0, 0, 0, 0, 0, 0, 0, 0, 0, 0]], "list_len": [18, 18, 12, 24, 24, 24, 12, 24, 24, 12, 24, 12, 24, 12, 24, 12, 12, 12], "pres_rate": [1200, 1200, 1600, 800, 800, 1600, 1600, 1600, 1600, 1600, 800, 1600, 800, 800, 1600, 800, 800, 800], "pres_mod": ["v", "v", "v", "v", "v", "v", "v", "v", "v", "v", "v", "v", "v", "v", "v", "v", "v", "v"], "dist_dur": [18000, 18000, 24000, 24000, 12000, 24000, 12000, 12000, 24000, 24000, 12000, 12000, 24000, 24000, 12000, 24000, 12000, 12000], "math_correct": [[true, true, true, true, true, false, false, false, false], [true, true, true, true, true, true, false, false, false], [true, true, true, true, false, true, true, true, false], [true, true, true, true, true, true, true, true, true], [true, true, true, true, true, false, false, false, false], [true, true, true, true, true, false, true, true, false], [true, true, true, false, false, false, false, false, false], [true, true, true, true, false, false, false, false, false], [true, true, true, true, true, true, true, false, false], [true, true, true, true, true, true, false, true, true], [true, false, false, false, false, false, false, false, false], [true, true, true, true, false, false, false, false, false], [true, true, true, true, true, true, true, true, true], [true, true, true, true, true, true, false, false, false], [true, true, true, false, false, false, false, false, false], [true, true, true, true, true, false, true, true, false], [true, true, true, false, false, false, false, false, false], [false, true, false, false, false, false, false, false, false]], "rt": [[6067, 11400, 52145, 55768, 0, 0, 0, 0, 0, 0, 0, 0, 0, 0], [2934, 5089, 7186, 10937, 12362, 14885, 21942, 28913, 41388, 0, 0, 0, 0, 0], [2243, 4528, 10543, 13886, 16222, 18314, 19913, 22762, 41732, 0, 0, 0, 0, 0], [3275, 4875, 6237, 6887, 8697, 15201, 17014, 20983, 0, 0, 0, 0, 0, 0], [2488, 4400, 6308, 12891, 15050, 19230, 20795, 27898, 52536, 0, 0, 0, 0, 0], [2534, 4665, 7356, 10403, 12718, 17422, 20326, 23309, 29522, 33106, 36467, 38342, 48007, 51666], [5615, 7651, 9831, 11591, 13522, 17999, 19291, 28548, 36982, 41723, 48235, 0, 0, 0], [3051, 5355, 8317, 10940, 15878, 20974, 24482, 30863, 46800, 49421, 57335, 59880, 0, 0], [2137, 3712, 7301, 11313, 17854, 23766, 25468, 28693, 46771, 49131, 50638, 0, 0, 0], [4295, 7585, 10340, 46218, 48501, 0, 0, 0, 0, 0, 0, 0, 0, 0], [3086, 5324, 7656, 9056, 11558, 14709, 20959, 22817, 25457, 0, 0, 0, 0, 0], [3973, 6178, 8087, 9431, 19285, 48448, 0, 0, 0, 0, 0, 0, 0, 0], [1550, 3271, 8040, 9452, 12283, 14725, 19326, 24626, 28594, 38698, 49375, 56104, 0, 0], [2699, 4952, 6836, 14219, 28187, 0, 0, 0, 0, 0, 0, 0, 0, 0], [6200, 10538, 12196, 14521, 16348, 18175, 22545, 30442, 32542, 34605, 40421, 58562, 0, 0], [3691, 7020, 16362, 23339, 26754, 0, 0, 0, 0, 0, 0, 0, 0, 0], [2505, 4056, 6522, 11618, 0, 0, 0, 0, 0, 0, 0, 0, 0, 0], [3084, 4920, 6933, 19567, 0, 0, 0, 0, 0, 0, 0, 0, 0, 0]], "recalled": [[1.0, 0.0, 0.0, 0.0, 0.0, 0.0, 1.0, 0.0, 0.0, 0.0, 1.0, 0.0, 0.0, 0.0, 0.0, 0.0, 0.0, 0.0, NaN, NaN, NaN, NaN, NaN, NaN], [1.0, 0.0, 1.0, 0.0, 0.0, 1.0, 0.0, 0.0, 0.0, 0.0, 1.0, 1.0, 1.0, 0.0, 0.0, 1.0, 0.0, 1.0, NaN, NaN, NaN, NaN, NaN, NaN], [0.0, 0.0, 0.0, 1.0, 1.0, 1.0, 1.0, 0.0, 1.0, 0.0, 0.0, 1.0, NaN, NaN, NaN, NaN, NaN, NaN, NaN, NaN, NaN, NaN, NaN, NaN], [1.0, 1.0, 0.0, 1.0, 0.0, 1.0, 1.0, 0.0, 0.0, 0.0, 0.0, 0.0, 0.0, 0.0, 0.0, 0.0, 0.0, 0.0, 0.0, 0.0, 0.0, 0.0, 1.0, 1.0], [1.0, 1.0, 1.0, 0.0, 1.0, 0.0, 1.0, 0.0, 0.0, 0.0, 0.0, 0.0, 0.0, 0.0, 0.0, 0.0, 1.0, 1.0, 0.0, 0.0, 1.0, 0.0, 0.0, 0.0], [1.0, 1.0, 0.0, 1.0, 1.0, 1.0, 1.0, 1.0, 0.0, 0.0, 1.0, 0.0, 1.0, 0.0, 0.0, 1.0, 0.0, 1.0, 1.0, 0.0, 1.0, 0.0, 0.0, 1.0], [1.0, 1.0, 0.0, 1.0, 1.0, 1.0, 1.0, 1.0, 1.0, 1.0, 1.0, 1.0, NaN, NaN, NaN, NaN, NaN, NaN, NaN, NaN, NaN, NaN, NaN, NaN], [0.0, 1.0, 0.0, 1.0, 1.0, 1.0, 0.0, 0.0, 0.0, 1.0, 0.0, 0.0, 1.0, 1.0, 0.0, 1.0, 1.0, 0.0, 0.0, 0.0, 0.0, 0.0, 1.0, 1.0], [1.0, 0.0, 0.0, 1.0, 1.0, 1.0, 0.0, 1.0, 0.0, 1.0, 0.0, 0.0, 1.0, 0.0, 0.0, 0.0, 1.0, 0.0, 1.0, 1.0, 1.0, 1.0, 0.0, 0.0], [1.0, 0.0, 0.0, 0.0, 1.0, 1.0, 0.0, 0.0, 0.0, 0.0, 1.0, 1.0, NaN, NaN, NaN, NaN, NaN, NaN, NaN, NaN, NaN, NaN, NaN, NaN], [1.0, 1.0, 1.0, 1.0, 0.0, 0.0, 1.0, 0.0, 0.0, 0.0, 0.0, 0.0, 1.0, 1.0, 0.0, 0.0, 0.0, 0.0, 0.0, 0.0, 0.0, 0.0, 1.0, 1.0], [1.0, 1.0, 0.0, 0.0, 1.0, 0.0, 1.0, 0.0, 0.0, 0.0, 0.0, 1.0, NaN, NaN, NaN, NaN, NaN, NaN, NaN, NaN, NaN, NaN, NaN, NaN], [1.0, 1.0, 0.0, 0.0, 0.0, 1.0, 1.0, 1.0, 0.0, 1.0, 1.0, 1.0, 0.0, 0.0, 0.0, 0.0, 0.0, 0.0, 0.0, 1.0, 0.0, 0.0, 1.0, 1.0], [0.0, 0.0, 1.0, 0.0, 0.0, 0.0, 0.0, 0.0, 0.0, 1.0, 1.0, 1.0, NaN, NaN, NaN, NaN, NaN, NaN, NaN, NaN, NaN, NaN, NaN, NaN], [1.0, 1.0, 1.0, 0.0, 0.0, 1.0, 0.0, 0.0, 0.0, 1.0, 0.0, 1.0, 1.0, 0.0, 1.0, 0.0, 0.0, 0.0, 0.0, 0.0, 0.0, 0.0, 1.0, 0.0], [0.0, 0.0, 0.0, 0.0, 1.0, 1.0, 1.0, 0.0, 0.0, 0.0, 1.0, 1.0, NaN, NaN, NaN, NaN, NaN, NaN, NaN, NaN, NaN, NaN, NaN, NaN], [1.0, 0.0, 0.0, 0.0, 0.0, 0.0, 0.0, 0.0, 0.0, 0.0, 1.0, 1.0, NaN, NaN, NaN, NaN, NaN, NaN, NaN, NaN, NaN, NaN, NaN, NaN], [0.0, 0.0, 0.0, 0.0, 0.0, 0.0, 0.0, 0.0, 1.0, 0.0, 1.0, 1.0, NaN, NaN, NaN, NaN, NaN, NaN, NaN, NaN, NaN, NaN, NaN, NaN]], "ffr_recalled": [[0.0, 0.0, 0.0, 0.0, 0.0, 0.0, 0.0, 0.0, 0.0, 0.0, 0.0, 0.0, 0.0, 0.0, 0.0, 0.0, 0.0, 0.0, NaN, NaN, NaN, NaN, NaN, NaN], [0.0, 0.0, 0.0, 0.0, 0.0, 1.0, 0.0, 0.0, 0.0, 0.0, 1.0, 0.0, 0.0, 0.0, 0.0, 0.0, 0.0, 0.0, NaN, NaN, NaN, NaN, NaN, NaN], [0.0, 0.0, 0.0, 0.0, 0.0, 0.0, 0.0, 0.0, 0.0, 0.0, 0.0, 0.0, NaN, NaN, NaN, NaN, NaN, NaN, NaN, NaN, NaN, NaN, NaN, NaN], [0.0, 0.0, 0.0, 0.0, 0.0, 0.0, 0.0, 0.0, 0.0, 0.0, 0.0, 0.0, 0.0, 0.0, 0.0, 0.0, 0.0, 0.0, 0.0, 0.0, 0.0, 0.0, 0.0, 0.0], [0.0, 0.0, 0.0, 0.0, 0.0, 0.0, 0.0, 0.0, 0.0, 0.0, 0.0, 0.0, 0.0, 0.0, 0.0, 0.0, 0.0, 0.0, 0.0, 0.0, 0.0, 0.0, 0.0, 0.0], [1.0, 0.0, 0.0, 1.0, 0.0, 0.0, 0.0, 0.0, 1.0, 0.0, 0.0, 0.0, 1.0, 0.0, 1.0, 0.0, 0.0, 0.0, 1.0, 0.0, 0.0, 0.0, 0.0, 0.0], [1.0, 1.0, 0.0, 0.0, 1.0, 0.0, 0.0, 1.0, 1.0, 1.0, 1.0, 0.0, NaN, NaN, NaN, NaN, NaN, NaN, NaN, NaN, NaN, NaN, NaN, NaN], [0.0, 1.0, 0.0, 1.0, 0.0, 0.0, 0.0, 0.0, 0.0, 0.0, 0.0, 1.0, 1.0, 1.0, 0.0, 1.0, 0.0, 0.0, 0.0, 0.0, 0.0, 0.0, 0.0, 0.0], [1.0, 0.0, 0.0, 1.0, 0.0, 0.0, 0.0, 1.0, 1.0, 0.0, 0.0, 0.0, 0.0, 0.0, 0.0, 0.0, 0.0, 0.0, 0.0, 0.0, 0.0, 0.0, 0.0, 0.0], [0.0, 0.0, 0.0, 0.0, 1.0, 1.0, 1.0, 1.0, 0.0, 0.0, 0.0, 0.0, NaN, NaN, NaN, NaN, NaN, NaN, NaN, NaN, NaN, NaN, NaN, NaN], [0.0, 0.0, 1.0, 0.0, 0.0, 0.0, 1.0, 0.0, 0.0, 0.0, 0.0, 0.0, 1.0, 1.0, 0.0, 0.0, 0.0, 0.0, 0.0, 0.0, 0.0, 0.0, 0.0, 0.0], [0.0, 0.0, 0.0, 0.0, 0.0, 0.0, 1.0, 0.0, 0.0, 0.0, 0.0, 0.0, NaN, NaN, NaN, NaN, NaN, NaN, NaN, NaN, NaN, NaN, NaN, NaN], [1.0, 1.0, 0.0, 0.0, 0.0, 1.0, 1.0, 0.0, 0.0, 0.0, 1.0, 1.0, 0.0, 1.0, 0.0, 0.0, 0.0, 0.0, 0.0, 0.0, 0.0, 0.0, 0.0, 0.0], [0.0, 0.0, 0.0, 0.0, 0.0, 0.0, 0.0, 0.0, 0.0, 0.0, 0.0, 0.0, NaN, NaN, NaN, NaN, NaN, NaN, NaN, NaN, NaN, NaN, NaN, NaN], [0.0, 0.0, 0.0, 0.0, 0.0, 0.0, 0.0, 0.0, 0.0, 0.0, 0.0, 0.0, 0.0, 0.0, 0.0, 0.0, 0.0, 0.0, 0.0, 0.0, 0.0, 0.0, 0.0, 0.0], [1.0, 0.0, 0.0, 0.0, 0.0, 0.0, 0.0, 0.0, 0.0, 0.0, 0.0, 0.0, NaN, NaN, NaN, NaN, NaN, NaN, NaN, NaN, NaN, NaN, NaN, NaN], [0.0, 0.0, 0.0, 0.0, 0.0, 0.0, 0.0, 0.0, 0.0, 0.0, 0.0, 0.0, NaN, NaN, NaN, NaN, NaN, NaN, NaN, NaN, NaN, NaN, NaN, NaN], [0.0, 0.0, 0.0, 0.0, 1.0, 0.0, 0.0, 0.0, 0.0, 1.0, 1.0, 1.0, NaN, NaN, NaN, NaN, NaN, NaN, NaN, NaN, NaN, NaN, NaN, NaN]], "ffr_rt": [4387, 5783, 8035, 12229, 16119, 19175, 22779, 26286, 29220, 31084, 34498, 39398, 40627, 51524, 55386, 59589, 68828, 76964, 78272, 84591, 85809, 91331, 97190, 100834, 102458, 104691, 107773, 111010, 128985, 139221, 141999, 144732, 157164, 162852, 164854, 166276, 176167, 178084, 189073, 208146, 221010, 222063, 231732, 236932, 239057, 269294, 272533, 296075, 298085], "subject": ["MTK1538", "MTK1538", "MTK1538", "MTK1538", "MTK1538", "MTK1538", "MTK1538", "MTK1538", "MTK1538", "MTK1538", "MTK1538", "MTK1538", "MTK1538", "MTK1538", "MTK1538", "MTK1538", "MTK1538", "MTK1538"], "intrusions": [[0, 0, 0, -1, 0, 0, 0, 0, 0, 0, 0, 0, 0, 0], [0, 0, 0, 0, 0, 0, 0, 0, 0, 0, 0, 0, 0, 0], [0, 0, 0, -1, 0, 0, -1, 0, 1, 0, 0, 0, 0, 0], [0, 0, 0, -1, 0, 0, 0, 0, 0, 0, 0, 0, 0, 0], [0, 0, 0, 0, 0, 0, 0, 0, 1, 0, 0, 0, 0, 0], [0, 0, 0, 0, 0, 0, 0, 0, 0, 0, 0, 0, 0, 0], [0, 0, 0, 0, 0, 0, 0, 0, 0, 0, 0, 0, 0, 0], [0, 0, 0, 0, 0, 0, 0, 0, 0, 0, 0, -1, 0, 0], [0, 0, 0, 0, 0, 0, 0, 0, 0, 0, 0, 0, 0, 0], [0, 0, 0, 0, 0, 0, 0, 0, 0, 0, 0, 0, 0, 0], [0, 0, 0, 0, 0, 0, 0, 0, 0, 0, 0, 0, 0, 0], [0, 0, 0, 0, 0, 0, 0, 0, 0, 0, 0, 0, 0, 0], [0, 0, 0, 0, 0, 0, 0, 0, 0, 0, 0, 0, 0, 0], [0, 0, 0, 0, 1, 0, 0, 0, 0, 0, 0, 0, 0, 0], [0, 0, 0, 11, 0, 0, 0, 0, 6, 6, 0, 0, 0, 0], [0, 0, 0, 0, 0, 0, 0, 0, 0, 0, 0, 0, 0, 0], [0, 0, 0, 0, 0, 0, 0, 0, 0, 0, 0, 0, 0, 0], [11, 0, 0, 0, 0, 0, 0, 0, 0, 0, 0, 0, 0, 0]]}