{"serialpos": [[9, 14, -999, -999, -999, -999, 0], [11, 6, 2, 4, 0, 0, 0], [16, 15, 22, 1, 5, 2, 7], [-999, 4, -999, 2, 7, 10, 9], [4, 9, 2, 3, 5, -999, -999], [-999, -1, 3, 10, 0, 0, 0], [-4, 3, 0, 0, 0, 0, 0], [5, -999, 2, -999, 10, 0, 0], [4, -999, 11, -999, 0, 0, 0], [-1, -999, -999, -999, -999, 9, -5], [-999, 1, 2, 3, -999, 11, 0], [-999, -999, 6, -999, 0, 0, 0], [-1, -12, 8, 0, 0, 0, 0], [-999, -999, 8, 0, 0, 0, 0], [21, 24, -999, -13, -999, 0, 0], [2, -999, 11, -999, -999, -4, 0], [-4, -999, -999, -7, 0, 0, 0], [9, -999, -999, -999, 0, 0, 0]], "ffr_serialpos": [2, 8, 13, 22, -999, -999, 7, 3, 4, 1, 10, 16, 9, 5, 6, 8, 10, 9, 12, 22, -999, -999, 2, 2, 3, 3, -999, 4, 5, 6, 8, -999, -999, 11, 13], "ffr_pres_trial": [15, 13, 4, 14, -999, -999, 3, 4, 4, 7, 16, 2, 4, 7, 7, 7, 7, 17, 7, 2, -999, -999, 4, 2, 5, 5, -999, 1, 4, 1, 1, -999, -999, 1, 1], "rec_words": [["venus", "mammal", "plus", "slash", "divide", "h", 0], ["orange", "salad", "costume", "donor", 0, 0, 0], ["truck", "driver", "ox", "waiter", "dragon", "parrot", "boyfriend"], ["iron", "zebra", "ideal", "poison", "shirt", "glass", "spool"], ["dress", "college", "peanut", "perfume", "clothes", "huge", "garment"], ["island", "perfume", "husband", "spouse", 0, 0, 0], ["chest", "fungus", 0, 0, 0, 0, 0], ["apple", "again", "lake", "happy", "world", 0, 0], ["stone", "jerry", "expert", "catch", 0, 0, 0], ["judge", "lee", "french", "splash", "hoster", "pizza", "cook"], ["tiger", "servant", "rocket", "cashier", "mission", "typist", 0], ["hello", "ladies", "dustpan", "dial", 0, 0, 0], ["turtle", "jungle", "patient", 0, 0, 0, 0], ["canteen", "neckless", "cricket", 0, 0, 0, 0], ["child", "forest", "snuck", "partner", "slop", 0, 0], ["match", "nine", "lunch", "oxter", "habit", "creature", 0], ["teacher", "ocean", "sharp", "marsh", 0, 0, 0], ["finger", "fortune", "link", "clow", 0, 0, 0]], "ffr_rec_words": ["match", "cricket", "window", "spider", "iron", "spice", "shirt", "perfume", "dress", "onion", "tractor", "truck", "college", "apple", "puppy", "cloud", "world", "finger", "fragrance", "ox", "island", "french", "peanut", "parrot", "husband", "husband", "ocean", "donor", "clothes", "salad", "bug", "peace", "point", "orange", "river"], "pres_words": [["flask", "jungle", "smog", "twister", "suspect", "hedge", "whiskers", "burglar", "venus", "country", "brother", "airplane", "flipper", "mammal", "diver", "perch", "scarf", "lace", 0, 0, 0, 0, 0, 0], ["shortcake", "costume", "lightning", "donor", "slug", "salad", "braces", "bug", "space", "popcorn", "orange", "fiddle", "river", "outfit", "pudding", "partner", "valley", "drink", 0, 0, 0, 0, 0, 0], ["waiter", "parrot", "pliers", "sunset", "dragon", "cousin", "boyfriend", "hood", "goblin", "cross", "slime", "tart", "scissors", "gavel", "driver", "truck", "chest", "motel", "palace", "tweezers", "sphinx", "ox", "ghetto", "rifle"], ["item", "poison", "twig", "zebra", "panther", "zipper", "shirt", "carrot", "spool", "glass", "lapel", "rod", 0, 0, 0, 0, 0, 0, 0, 0, 0, 0, 0, 0], ["motor", "peanut", "perfume", "dress", "clothes", "softball", "sticker", "piano", "college", "garlic", "cook", "harp", "window", "pecan", "peach", "sheriff", "stove", "pebble", "mailbox", "knapsack", "padding", "denim", "tourist", "county"], ["france", "japan", "husband", "sausage", "ozone", "flashlight", "razor", "fleet", "eyelash", "spouse", "skillet", "banquet", 0, 0, 0, 0, 0, 0, 0, 0, 0, 0, 0, 0], ["beast", "rabbit", "fungus", "dashboard", "camel", "salmon", "trout", "cupboard", "chipmunk", "queen", "monster", "banker", "london", "lady", "trombone", "daisy", "lumber", "sketch", "nightgown", "widow", "donkey", "marrow", "liver", "flute"], ["onion", "lake", "orchid", "garden", "apple", "puppy", "blouse", "cloud", "passage", "world", "human", "fragrance", 0, 0, 0, 0, 0, 0, 0, 0, 0, 0, 0, 0], ["body", "critic", "brick", "stone", "jury", "shelf", "cellar", "brandy", "army", "judge", "expert", "quarter", 0, 0, 0, 0, 0, 0, 0, 0, 0, 0, 0, 0], ["statue", "blade", "branch", "cocoon", "flesh", "tombstone", "church", "pasta", "pizza", "author", "saddle", "seal", "couch", "yarn", "lagoon", "marsh", "robot", "princess", "office", "subway", "mattress", "pocket", "snake", "freezer"], ["servant", "rocket", "cashier", "robber", "nomad", "carriage", "cobra", "diner", "airport", "missile", "typist", "barley", 0, 0, 0, 0, 0, 0, 0, 0, 0, 0, 0, 0], ["lettuce", "radish", "turtle", "puddle", "bunny", "dustpan", "tile", "grave", "curtain", "omelet", "creature", "binder", 0, 0, 0, 0, 0, 0, 0, 0, 0, 0, 0, 0], ["fruit", "comet", "swimmer", "gymnast", "viking", "freckle", "dust", "patient", "teacher", "atom", "hiker", "flower", "barrel", "honey", "juggler", "cashew", "keeper", "bathtub", "stomach", "fireplace", "kitchen", "gallon", "picnic", "climber"], ["briefcase", "blueprint", "canyon", "citrus", "necklace", "sidewalk", "plaster", "cricket", "crib", "infant", "crown", "grape", 0, 0, 0, 0, 0, 0, 0, 0, 0, 0, 0, 0], ["swamp", "server", "ointment", "student", "rust", "suitcase", "knife", "sword", "wife", "dorm", "marker", "shovel", "candy", "lava", "bullet", "staple", "female", "survey", "guitar", "tuba", "child", "spider", "snack", "forest"], ["asia", "match", "police", "parsley", "cabbage", "cabin", "cookbook", "lion", "europe", "oyster", "lunch", "whistle", 0, 0, 0, 0, 0, 0, 0, 0, 0, 0, 0, 0], ["quail", "icing", "wrench", "kleenex", "custard", "jelly", "turkey", "ulcer", "scarecrow", "tractor", "shrub", "table", "shoulder", "hand", "package", "fox", "ankle", "bacon", "leg", "snail", "tortoise", "leader", "backbone", "bouquet"], ["wrist", "rebel", "hornet", "compass", "blockade", "hatchet", "lover", "egypt", "finger", "glove", "picture", "portrait", "woman", "daughter", "receipt", "hamper", "kidney", "robin", "pigment", "chauffeur", "wardrobe", "wasp", "sparrow", "frame"]], "list_len": [18, 18, 24, 12, 24, 12, 24, 12, 12, 24, 12, 12, 24, 12, 24, 12, 24, 24], "pres_rate": [1200, 1200, 1600, 800, 800, 800, 800, 800, 1600, 1600, 1600, 1600, 800, 1600, 1600, 800, 1600, 800], "pres_mod": ["a", "a", "a", "a", "a", "a", "a", "a", "a", "a", "a", "a", "a", "a", "a", "a", "a", "a"], "dist_dur": [18000, 18000, 24000, 12000, 24000, 24000, 24000, 12000, 24000, 12000, 12000, 12000, 12000, 24000, 12000, 24000, 24000, 12000], "math_correct": [[true, true, true, false, false, false, false, false, false, false, false], [true, true, true, true, true, false, false, false, false, false, false], [true, true, true, true, false, false, false, false, false, false, false], [true, true, true, false, false, false, false, false, false, false, false], [true, true, true, true, true, true, true, true, false, false, false], [true, true, true, true, true, true, true, false, false, false, false], [true, true, true, true, true, true, true, true, true, true, false], [true, true, true, false, false, false, false, false, false, false, false], [true, true, true, true, true, true, true, true, false, false, false], [true, true, true, true, false, false, false, false, false, false, false], [true, true, false, false, false, false, false, false, false, false, false], [true, true, true, true, false, false, false, false, false, false, false], [true, true, true, false, false, false, false, false, false, false, false], [true, true, true, true, true, true, true, true, true, true, true], [true, true, true, true, false, false, false, false, false, false, false], [true, true, true, true, true, true, true, false, false, false, false], [true, true, false, true, true, true, true, true, false, false, false], [true, true, true, false, false, false, false, false, false, false, false]], "rt": [[14091, 18379, 22995, 37003, 46148, 58123, 0], [24450, 35600, 47432, 57536, 0, 0, 0], [9369, 13248, 20289, 31628, 37684, 42740, 54197], [4708, 12602, 22584, 33303, 39455, 45784, 50712], [3405, 7982, 15422, 23432, 37222, 46528, 54617], [8623, 16152, 24424, 40257, 0, 0, 0], [33891, 43653, 0, 0, 0, 0, 0], [12127, 16811, 25206, 32819, 41924, 0, 0], [11596, 15749, 24548, 39487, 0, 0, 0], [10425, 15064, 20829, 28448, 33544, 43960, 57453], [7588, 14446, 20468, 28740, 36520, 44387, 0], [9628, 16157, 49028, 53877, 0, 0, 0], [10419, 26971, 43099, 0, 0, 0, 0], [10762, 17873, 50923, 0, 0, 0, 0], [11115, 15867, 33492, 40831, 53787, 0, 0], [8531, 11987, 16833, 22866, 38273, 53890, 0], [17348, 29604, 38015, 55996, 0, 0, 0], [10606, 20238, 36543, 54613, 0, 0, 0]], "recalled": [[0.0, 1.0, 0.0, 0.0, 0.0, 0.0, 0.0, 0.0, 1.0, 0.0, 0.0, 0.0, 0.0, 1.0, 0.0, 0.0, 0.0, 0.0, NaN, NaN, NaN, NaN, NaN, NaN], [0.0, 1.0, 0.0, 1.0, 0.0, 1.0, 0.0, 0.0, 0.0, 0.0, 1.0, 0.0, 0.0, 0.0, 0.0, 1.0, 0.0, 0.0, NaN, NaN, NaN, NaN, NaN, NaN], [1.0, 1.0, 0.0, 0.0, 1.0, 0.0, 1.0, 0.0, 0.0, 0.0, 0.0, 0.0, 0.0, 0.0, 1.0, 1.0, 1.0, 0.0, 0.0, 0.0, 0.0, 1.0, 0.0, 0.0], [0.0, 1.0, 0.0, 1.0, 0.0, 0.0, 1.0, 0.0, 1.0, 1.0, 0.0, 0.0, NaN, NaN, NaN, NaN, NaN, NaN, NaN, NaN, NaN, NaN, NaN, NaN], [0.0, 1.0, 1.0, 1.0, 1.0, 0.0, 0.0, 0.0, 1.0, 0.0, 1.0, 0.0, 0.0, 0.0, 0.0, 0.0, 0.0, 0.0, 0.0, 0.0, 0.0, 0.0, 0.0, 0.0], [0.0, 0.0, 1.0, 0.0, 0.0, 0.0, 0.0, 0.0, 0.0, 1.0, 0.0, 0.0, NaN, NaN, NaN, NaN, NaN, NaN, NaN, NaN, NaN, NaN, NaN, NaN], [0.0, 0.0, 1.0, 0.0, 0.0, 0.0, 0.0, 0.0, 0.0, 0.0, 0.0, 0.0, 0.0, 0.0, 0.0, 0.0, 0.0, 0.0, 0.0, 0.0, 0.0, 0.0, 0.0, 0.0], [0.0, 1.0, 0.0, 0.0, 1.0, 0.0, 0.0, 0.0, 0.0, 1.0, 0.0, 0.0, NaN, NaN, NaN, NaN, NaN, NaN, NaN, NaN, NaN, NaN, NaN, NaN], [0.0, 0.0, 0.0, 1.0, 0.0, 0.0, 0.0, 0.0, 0.0, 1.0, 1.0, 0.0, NaN, NaN, NaN, NaN, NaN, NaN, NaN, NaN, NaN, NaN, NaN, NaN], [0.0, 0.0, 0.0, 0.0, 0.0, 0.0, 0.0, 0.0, 1.0, 0.0, 0.0, 0.0, 0.0, 0.0, 0.0, 1.0, 0.0, 0.0, 0.0, 0.0, 0.0, 0.0, 0.0, 0.0], [1.0, 1.0, 1.0, 0.0, 0.0, 0.0, 0.0, 0.0, 0.0, 0.0, 1.0, 0.0, NaN, NaN, NaN, NaN, NaN, NaN, NaN, NaN, NaN, NaN, NaN, NaN], [0.0, 0.0, 1.0, 0.0, 0.0, 1.0, 0.0, 0.0, 0.0, 0.0, 1.0, 0.0, NaN, NaN, NaN, NaN, NaN, NaN, NaN, NaN, NaN, NaN, NaN, NaN], [0.0, 0.0, 0.0, 0.0, 0.0, 0.0, 0.0, 1.0, 1.0, 0.0, 0.0, 0.0, 0.0, 0.0, 0.0, 0.0, 0.0, 0.0, 0.0, 0.0, 0.0, 0.0, 0.0, 0.0], [0.0, 0.0, 0.0, 0.0, 0.0, 0.0, 0.0, 1.0, 0.0, 0.0, 0.0, 0.0, NaN, NaN, NaN, NaN, NaN, NaN, NaN, NaN, NaN, NaN, NaN, NaN], [0.0, 0.0, 0.0, 0.0, 0.0, 0.0, 0.0, 0.0, 0.0, 0.0, 0.0, 0.0, 0.0, 0.0, 0.0, 0.0, 0.0, 0.0, 0.0, 0.0, 1.0, 0.0, 0.0, 1.0], [0.0, 1.0, 0.0, 0.0, 0.0, 0.0, 0.0, 0.0, 0.0, 0.0, 1.0, 0.0, NaN, NaN, NaN, NaN, NaN, NaN, NaN, NaN, NaN, NaN, NaN, NaN], [0.0, 0.0, 0.0, 0.0, 0.0, 0.0, 0.0, 0.0, 0.0, 0.0, 0.0, 0.0, 0.0, 0.0, 0.0, 0.0, 0.0, 0.0, 0.0, 0.0, 0.0, 0.0, 0.0, 0.0], [0.0, 0.0, 0.0, 0.0, 0.0, 0.0, 0.0, 0.0, 1.0, 0.0, 0.0, 0.0, 0.0, 0.0, 0.0, 0.0, 0.0, 0.0, 0.0, 0.0, 0.0, 0.0, 0.0, 0.0]], "ffr_recalled": [[0.0, 0.0, 0.0, 0.0, 0.0, 0.0, 0.0, 0.0, 0.0, 0.0, 0.0, 0.0, 0.0, 0.0, 0.0, 0.0, 0.0, 0.0, NaN, NaN, NaN, NaN, NaN, NaN], [0.0, 0.0, 0.0, 1.0, 0.0, 1.0, 0.0, 1.0, 0.0, 0.0, 1.0, 0.0, 1.0, 0.0, 0.0, 0.0, 0.0, 0.0, NaN, NaN, NaN, NaN, NaN, NaN], [0.0, 1.0, 0.0, 0.0, 0.0, 0.0, 0.0, 0.0, 0.0, 0.0, 0.0, 0.0, 0.0, 0.0, 0.0, 1.0, 0.0, 0.0, 0.0, 0.0, 0.0, 1.0, 0.0, 0.0], [0.0, 0.0, 0.0, 0.0, 0.0, 0.0, 1.0, 0.0, 0.0, 0.0, 0.0, 0.0, NaN, NaN, NaN, NaN, NaN, NaN, NaN, NaN, NaN, NaN, NaN, NaN], [0.0, 1.0, 1.0, 1.0, 1.0, 0.0, 0.0, 0.0, 1.0, 0.0, 0.0, 0.0, 1.0, 0.0, 0.0, 0.0, 0.0, 0.0, 0.0, 0.0, 0.0, 0.0, 0.0, 0.0], [0.0, 0.0, 1.0, 0.0, 0.0, 0.0, 0.0, 0.0, 0.0, 0.0, 0.0, 0.0, NaN, NaN, NaN, NaN, NaN, NaN, NaN, NaN, NaN, NaN, NaN, NaN], [0.0, 0.0, 0.0, 0.0, 0.0, 0.0, 0.0, 0.0, 0.0, 0.0, 0.0, 0.0, 0.0, 0.0, 0.0, 0.0, 0.0, 0.0, 0.0, 0.0, 0.0, 0.0, 0.0, 0.0], [1.0, 0.0, 0.0, 0.0, 1.0, 1.0, 0.0, 1.0, 0.0, 1.0, 0.0, 1.0, NaN, NaN, NaN, NaN, NaN, NaN, NaN, NaN, NaN, NaN, NaN, NaN], [0.0, 0.0, 0.0, 0.0, 0.0, 0.0, 0.0, 0.0, 0.0, 0.0, 0.0, 0.0, NaN, NaN, NaN, NaN, NaN, NaN, NaN, NaN, NaN, NaN, NaN, NaN], [0.0, 0.0, 0.0, 0.0, 0.0, 0.0, 0.0, 0.0, 0.0, 0.0, 0.0, 0.0, 0.0, 0.0, 0.0, 0.0, 0.0, 0.0, 0.0, 0.0, 0.0, 0.0, 0.0, 0.0], [0.0, 0.0, 0.0, 0.0, 0.0, 0.0, 0.0, 0.0, 0.0, 0.0, 0.0, 0.0, NaN, NaN, NaN, NaN, NaN, NaN, NaN, NaN, NaN, NaN, NaN, NaN], [0.0, 0.0, 0.0, 0.0, 0.0, 0.0, 0.0, 0.0, 0.0, 0.0, 0.0, 0.0, NaN, NaN, NaN, NaN, NaN, NaN, NaN, NaN, NaN, NaN, NaN, NaN], [0.0, 0.0, 0.0, 0.0, 0.0, 0.0, 0.0, 0.0, 0.0, 0.0, 0.0, 0.0, 0.0, 0.0, 0.0, 0.0, 0.0, 0.0, 0.0, 0.0, 0.0, 0.0, 0.0, 0.0], [0.0, 0.0, 0.0, 0.0, 0.0, 0.0, 0.0, 1.0, 0.0, 0.0, 0.0, 0.0, NaN, NaN, NaN, NaN, NaN, NaN, NaN, NaN, NaN, NaN, NaN, NaN], [0.0, 0.0, 0.0, 0.0, 0.0, 0.0, 0.0, 0.0, 0.0, 0.0, 0.0, 0.0, 0.0, 0.0, 0.0, 0.0, 0.0, 0.0, 0.0, 0.0, 0.0, 1.0, 0.0, 0.0], [0.0, 1.0, 0.0, 0.0, 0.0, 0.0, 0.0, 0.0, 0.0, 0.0, 0.0, 0.0, NaN, NaN, NaN, NaN, NaN, NaN, NaN, NaN, NaN, NaN, NaN, NaN], [0.0, 0.0, 0.0, 0.0, 0.0, 0.0, 0.0, 0.0, 0.0, 1.0, 0.0, 0.0, 0.0, 0.0, 0.0, 0.0, 0.0, 0.0, 0.0, 0.0, 0.0, 0.0, 0.0, 0.0], [0.0, 0.0, 0.0, 0.0, 0.0, 0.0, 0.0, 0.0, 1.0, 0.0, 0.0, 0.0, 0.0, 0.0, 0.0, 0.0, 0.0, 0.0, 0.0, 0.0, 0.0, 0.0, 0.0, 0.0]], "ffr_rt": [7241, 13736, 19849, 31328, 36928, 42896, 47815, 55090, 64866, 71699, 86641, 91451, 103328, 106826, 113545, 126123, 137625, 144729, 157120, 166465, 173153, 184553, 195490, 200034, 205858, 213737, 222843, 244200, 251249, 260568, 270960, 277889, 282240, 286553, 293900], "subject": ["MTK3771", "MTK3771", "MTK3771", "MTK3771", "MTK3771", "MTK3771", "MTK3771", "MTK3771", "MTK3771", "MTK3771", "MTK3771", "MTK3771", "MTK3771", "MTK3771", "MTK3771", "MTK3771", "MTK3771", "MTK3771"], "intrusions": [[0, 0, -1, -1, -1, -1, 0], [0, 0, 0, 0, 0, 0, 0], [0, 0, 0, 0, 0, 0, 0], [-1, 0, -1, 0, 0, 0, 0], [0, 0, 0, 0, 0, -1, -1], [-1, 1, 0, 0, 0, 0, 0], [4, 0, 0, 0, 0, 0, 0], [0, -1, 0, -1, 0, 0, 0], [0, -1, 0, -1, 0, 0, 0], [1, -1, -1, -1, -1, 0, 5], [-1, 0, 0, 0, -1, 0, 0], [-1, -1, 0, -1, 0, 0, 0], [1, 12, 0, 0, 0, 0, 0], [-1, -1, 0, 0, 0, 0, 0], [0, 0, -1, 13, -1, 0, 0], [0, -1, 0, -1, -1, 4, 0], [4, -1, -1, 7, 0, 0, 0], [0, -1, -1, -1, 0, 0, 0]]}