{"serialpos": [[1, 2, 3, 2, 17, -999, 0, 0, 0, 0, 0, 0], [18, -999, -1, 18, 16, 7, 0, 0, 0, 0, 0, 0], [-999, -999, 3, -999, 4, -999, -999, 8, 9, 11, 12, 0], [-999, 2, 3, 4, 5, 6, 7, -999, 9, 10, 11, 0], [1, 2, -999, 5, 6, 7, 10, 12, 0, 0, 0, 0], [1, 2, 3, 4, 5, -999, 6, -999, -999, 9, 11, -999], [1, 2, 3, 4, 5, 8, 9, 12, 13, 14, -999, -999], [-999, 2, 3, 4, 5, 6, 7, 8, 9, 10, -999, 12], [-999, 3, -999, -999, -999, 7, 9, -999, -2, 12, -999, 15], [1, 2, 5, 7, 8, 10, 9, 11, -999, 0, 0, 0], [1, 3, 4, 6, 7, -999, 9, 10, -999, 0, 0, 0], [-999, 3, -999, 6, 7, 8, 9, 14, 16, 17, 18, -999], [1, 2, 4, -8, 6, 7, -1, 11, -999, 19, 0, 0], [2, 6, 7, 8, 12, 16, 18, 20, -999, 23, 0, 0], [-999, 6, 10, 5, 13, 16, 17, 21, 23, 0, 0, 0], [1, 4, 7, 5, 9, -999, 12, 15, 0, 0, 0, 0], [1, 3, -999, 9, 11, 0, 0, 0, 0, 0, 0, 0], [-999, 4, 3, 8, 9, -999, 11, 12, 0, 0, 0, 0]], "ffr_serialpos": [5, -999, -999, 9, 3, 4, 15, 4, 6, 21, 21, 6, 7, 2, 1, 10, 12, 7, 7, -999, 2, -999, 5, 12, 4, 3, 12, 4, 5, 5], "ffr_pres_trial": [17, -999, -999, 16, 17, 17, 15, 15, 14, 14, 11, 12, 13, 9, 9, 10, 8, 7, 7, -999, 6, -999, 3, 6, 5, 8, 7, 10, 9, 9], "rec_words": [["princess", "highway", "forehead", "highway", "robot", "formula", 0, 0, 0, 0, 0, 0], ["supper", "labor", "highway", "supper", "label", "picture", 0, 0, 0, 0, 0, 0], ["tomato", "spice", "sunset", "rise", "sunrise", "light", "high", "climber", "diver", "citrus", "woman", 0], ["temper", "swamp", "husband", "freckle", "gravel", "rocket", "missile", "pinic", "lumber", "mattress", "friend", 0], ["saddle", "world", "waiter", "scarf", "salt", "cocktail", "gymnast", "partner", 0, 0, 0, 0], ["ghetto", "nurse", "donor", "elbow", "compass", "trama", "frame", "scrub", "scapple", "mammal", "twister", "winter"], ["omelet", "mars", "item", "shirt", "puddle", "bacon", "creature", "lady", "scotch", "seagull", "knot", "aware"], ["pod", "piston", "hornet", "loft", "crab", "eyelash", "pecan", "washer", "sidewalk", "rifle", "anchor", "bank"], ["cork", "robber", "port", "leaper", "chunk", "stomach", "apple", "supple", "creature", "yacht", "dummy", "camel"], ["popcorn", "soda", "tunnel", "pudding", "wagon", "liver", "banjo", "custard", "sail", 0, 0, 0], ["oyster", "shovel", "drug", "trombone", "mailman", "slaughter", "child", "sheriff", "sharp", 0, 0, 0], ["burglar", "pocket", "paddle", "puppy", "swimmer", "silk", "worker", "snake", "ozone", "flag", "stamp", "bungle"], ["outlaw", "river", "sketch", "blouse", "icing", "pimple", "guitar", "onion", "donet", "muffin", 0, 0], ["radish", "mildew", "dorm", "cafe", "turnip", "twig", "stove", "fox", "ankle", "market", 0, 0], ["vale", "clock", "japan", "france", "lava", "office", "blade", "glove", "cashier", 0, 0, 0], ["handbag", "piano", "wasp", "necklace", "shorts", "den", "dentist", "fleet", 0, 0, 0, 0], ["star", "lettuce", "scissor", "salmon", "tortoise", 0, 0, 0, 0, 0, 0, 0], ["porch", "lake", "mummy", "lion", "film", "waiter", "hostess", "actor", 0, 0, 0, 0]], "ffr_rec_words": ["salad", "waiter", "scissor", "salmon", "mummy", "lake", "fleet", "piano", "clock", "glove", "clothes", "icing", "dorm", "soda", "popcorn", "sheriff", "yacht", "pecan", "pecan", "twist", "mars", "light", "gravel", "lady", "elbow", "robber", "bank", "drug", "tunnel", "tunnel"], "pres_words": [["princess", "highway", "forehead", "passage", "yarn", "maple", "thief", "college", "stream", "dandruff", "scallop", "hedge", "sword", "knapsack", "butcher", "pizza", "robot", "velvet", 0, 0, 0, 0, 0, 0], ["monster", "flipper", "beaker", "hood", "patrol", "plaster", "picture", "machine", "casket", "igloo", "cowboy", "portrait", "canal", "pluto", "tweezers", "label", "survey", "supper", 0, 0, 0, 0, 0, 0], ["tourist", "space", "sunset", "sunrise", "grape", "lightning", "peach", "climber", "diver", "fragrance", "citrus", "woman", 0, 0, 0, 0, 0, 0, 0, 0, 0, 0, 0, 0], ["keeper", "swamp", "husband", "freckle", "gravel", "rocket", "missile", "picnic", "lumber", "mattress", "friend", "author", 0, 0, 0, 0, 0, 0, 0, 0, 0, 0, 0, 0], ["saddle", "world", "blouse", "wardrobe", "scarf", "salt", "cocktail", "country", "lover", "gymnast", "guard", "partner", 0, 0, 0, 0, 0, 0, 0, 0, 0, 0, 0, 0], ["ghetto", "nurse", "donor", "elbow", "compass", "frame", "shrub", "scalpel", "mammal", "lizard", "twister", "garden", "window", "spouse", "garlic", "pepper", "money", "wife", "braces", "bouquet", "statue", "seal", "lace", "record"], ["omelet", "mars", "item", "shirt", "puddle", "dust", "cross", "bacon", "creature", "beast", "marker", "lady", "scotch", "seagull", "leader", "contract", "arm", "knife", "brandy", "backbone", "award", "pastry", "pasta", "chipmunk"], ["cod", "piston", "hornet", "loft", "crab", "eyelash", "pecan", "washer", "sidewalk", "rifle", "banker", "bank", 0, 0, 0, 0, 0, 0, 0, 0, 0, 0, 0, 0], ["pork", "cookbook", "robber", "poet", "leopard", "chest", "stomach", "basement", "apple", "suspect", "preacher", "yacht", "jelly", "nightgown", "camel", "cabbage", "servant", "headband", "seafood", "drink", "parsley", "europe", "asia", "diner"], ["popcorn", "soda", "shortcake", "hatchet", "tunnel", "flower", "pudding", "wagon", "banjo", "liver", "custard", "quail", 0, 0, 0, 0, 0, 0, 0, 0, 0, 0, 0, 0], ["oyster", "hamper", "shovel", "drug", "transplant", "trombone", "mailman", "daughter", "child", "sheriff", "blockade", "harp", 0, 0, 0, 0, 0, 0, 0, 0, 0, 0, 0, 0], ["drawing", "briefcase", "pocket", "valley", "cattle", "puppy", "swimmer", "silk", "worker", "powder", "milk", "canyon", "sibling", "snake", "truck", "ozone", "flag", "stamp", "cobra", "jungle", "clothes", "guitar", "tuba", "sticker"], ["outlaw", "river", "luggage", "sketch", "blackboard", "icing", "pimple", "suitcase", "cupboard", "dresser", "onion", "cigar", "journal", "bathtub", "costume", "dress", "doughnut", "denim", "muffin", "scribble", "proton", "parrot", "church", "snack"], ["shoulder", "radish", "patient", "antler", "binder", "mildew", "dorm", "cafe", "blueprint", "fiddle", "flute", "turnip", "gazelle", "napkin", "rabbit", "twig", "slug", "stove", "toaster", "fox", "banquet", "staple", "market", "tablet"], ["temple", "valve", "dustpan", "motel", "france", "clock", "tart", "queen", "gallon", "japan", "blender", "skillet", "lava", "sandwich", "sausage", "office", "blade", "pilot", "driver", "carrot", "glove", "rod", "cashier", "crater"], ["handbag", "wrench", "fungus", "piano", "necklace", "spider", "wasp", "branch", "shorts", "plaid", "dragon", "dentist", "gavel", "shelter", "fleet", "jury", "tractor", "crib", "ulcer", "judge", "relish", "zebra", "panther", "agent"], ["star", "shark", "lettuce", "razor", "finger", "breast", "scissors", "infant", "salmon", "snail", "tortoise", "curtain", 0, 0, 0, 0, 0, 0, 0, 0, 0, 0, 0, 0], ["perch", "termite", "mummy", "lake", "salad", "convict", "tile", "lion", "film", "waitress", "hostess", "actor", 0, 0, 0, 0, 0, 0, 0, 0, 0, 0, 0, 0]], "list_len": [18, 18, 12, 12, 12, 24, 24, 12, 24, 12, 12, 24, 24, 24, 24, 24, 12, 12], "pres_rate": [1200, 1200, 800, 1600, 800, 1600, 800, 1600, 800, 1600, 1600, 800, 800, 1600, 1600, 1600, 800, 800], "pres_mod": ["a", "a", "a", "a", "a", "a", "a", "a", "a", "a", "a", "a", "a", "a", "a", "a", "a", "a"], "dist_dur": [18000, 18000, 24000, 24000, 12000, 12000, 24000, 12000, 12000, 12000, 24000, 24000, 12000, 24000, 24000, 12000, 12000, 24000], "math_correct": [[true, true, false, false, false, false, false], [true, true, true, false, false, false, false], [true, true, true, true, true, false, false], [true, true, true, true, true, true, true], [true, true, false, false, false, false, false], [true, true, false, false, false, false, false], [true, true, true, true, true, false, false], [true, true, true, false, false, false, false], [true, true, true, false, false, false, false], [true, true, true, false, false, false, false], [true, true, true, true, true, false, false], [true, true, true, true, true, false, false], [true, true, false, false, false, false, false], [true, true, true, true, true, false, true], [true, true, true, true, true, true, false], [true, true, true, false, false, false, false], [true, true, false, false, false, false, false], [true, true, true, true, true, true, false]], "rt": [[6757, 10965, 16369, 20089, 25077, 45149, 0, 0, 0, 0, 0, 0], [16229, 21716, 27660, 32000, 38058, 41442, 0, 0, 0, 0, 0, 0], [7311, 10996, 15275, 18415, 28547, 31745, 37348, 41857, 46043, 52541, 57103, 0], [10729, 16088, 20369, 24875, 29593, 34287, 38407, 42833, 46964, 51661, 59179, 0], [6702, 11244, 17677, 23593, 27637, 34743, 45584, 55410, 0, 0, 0, 0], [6383, 10522, 15425, 20218, 24936, 30111, 34414, 37986, 45994, 50496, 54962, 59972], [6287, 8327, 11545, 14880, 20328, 25679, 30680, 34592, 38887, 43532, 51428, 57711], [5422, 9495, 14535, 17614, 21128, 25816, 29674, 33653, 37906, 41878, 46530, 49817], [4535, 8816, 12578, 16144, 21048, 26231, 29791, 37696, 44199, 47281, 54198, 59534], [6371, 10254, 14876, 20069, 24010, 27698, 30708, 47142, 56716, 0, 0, 0], [6654, 12381, 16058, 26255, 33311, 38680, 47534, 52710, 57459, 0, 0, 0], [10694, 14624, 19598, 23422, 28056, 30730, 38882, 41115, 45880, 50625, 54310, 59317], [8008, 13031, 17389, 23666, 31145, 36659, 41707, 45645, 51937, 59629, 0, 0], [7998, 12391, 17637, 21049, 27054, 31390, 36923, 42131, 48283, 55225, 0, 0], [5241, 10084, 17760, 21594, 28251, 38898, 41866, 46740, 55231, 0, 0, 0], [9973, 15351, 24203, 28297, 36514, 41999, 48087, 56151, 0, 0, 0, 0], [5978, 10685, 15325, 20874, 26962, 0, 0, 0, 0, 0, 0, 0], [8658, 12251, 18530, 21771, 26809, 32312, 41844, 48890, 0, 0, 0, 0]], "recalled": [[1.0, 1.0, 1.0, 0.0, 0.0, 0.0, 0.0, 0.0, 0.0, 0.0, 0.0, 0.0, 0.0, 0.0, 0.0, 0.0, 1.0, 0.0, NaN, NaN, NaN, NaN, NaN, NaN], [0.0, 0.0, 0.0, 0.0, 0.0, 0.0, 1.0, 0.0, 0.0, 0.0, 0.0, 0.0, 0.0, 0.0, 0.0, 1.0, 0.0, 1.0, NaN, NaN, NaN, NaN, NaN, NaN], [0.0, 0.0, 1.0, 1.0, 0.0, 0.0, 0.0, 1.0, 1.0, 0.0, 1.0, 1.0, NaN, NaN, NaN, NaN, NaN, NaN, NaN, NaN, NaN, NaN, NaN, NaN], [0.0, 1.0, 1.0, 1.0, 1.0, 1.0, 1.0, 0.0, 1.0, 1.0, 1.0, 0.0, NaN, NaN, NaN, NaN, NaN, NaN, NaN, NaN, NaN, NaN, NaN, NaN], [1.0, 1.0, 1.0, 0.0, 1.0, 1.0, 1.0, 0.0, 0.0, 1.0, 0.0, 1.0, NaN, NaN, NaN, NaN, NaN, NaN, NaN, NaN, NaN, NaN, NaN, NaN], [1.0, 1.0, 1.0, 1.0, 1.0, 1.0, 0.0, 0.0, 1.0, 0.0, 1.0, 0.0, 0.0, 0.0, 0.0, 0.0, 0.0, 0.0, 0.0, 0.0, 0.0, 0.0, 0.0, 0.0], [1.0, 1.0, 1.0, 1.0, 1.0, 0.0, 0.0, 1.0, 1.0, 0.0, 0.0, 1.0, 1.0, 1.0, 0.0, 0.0, 0.0, 0.0, 0.0, 0.0, 0.0, 0.0, 0.0, 0.0], [0.0, 1.0, 1.0, 1.0, 1.0, 1.0, 1.0, 1.0, 1.0, 1.0, 0.0, 1.0, NaN, NaN, NaN, NaN, NaN, NaN, NaN, NaN, NaN, NaN, NaN, NaN], [0.0, 0.0, 1.0, 0.0, 0.0, 0.0, 1.0, 0.0, 1.0, 0.0, 0.0, 1.0, 0.0, 0.0, 1.0, 0.0, 0.0, 0.0, 0.0, 0.0, 0.0, 0.0, 0.0, 0.0], [1.0, 1.0, 0.0, 0.0, 1.0, 0.0, 1.0, 1.0, 1.0, 1.0, 1.0, 0.0, NaN, NaN, NaN, NaN, NaN, NaN, NaN, NaN, NaN, NaN, NaN, NaN], [1.0, 0.0, 1.0, 1.0, 0.0, 1.0, 1.0, 0.0, 1.0, 1.0, 0.0, 0.0, NaN, NaN, NaN, NaN, NaN, NaN, NaN, NaN, NaN, NaN, NaN, NaN], [0.0, 0.0, 1.0, 0.0, 0.0, 1.0, 1.0, 1.0, 1.0, 0.0, 0.0, 0.0, 0.0, 1.0, 0.0, 1.0, 1.0, 1.0, 0.0, 0.0, 0.0, 1.0, 0.0, 0.0], [1.0, 1.0, 0.0, 1.0, 0.0, 1.0, 1.0, 0.0, 0.0, 0.0, 1.0, 0.0, 0.0, 0.0, 0.0, 0.0, 0.0, 0.0, 1.0, 0.0, 0.0, 0.0, 0.0, 0.0], [0.0, 1.0, 0.0, 0.0, 0.0, 1.0, 1.0, 1.0, 0.0, 0.0, 0.0, 1.0, 0.0, 0.0, 0.0, 1.0, 0.0, 1.0, 0.0, 1.0, 0.0, 0.0, 1.0, 0.0], [0.0, 0.0, 0.0, 0.0, 1.0, 1.0, 0.0, 0.0, 0.0, 1.0, 0.0, 0.0, 1.0, 0.0, 0.0, 1.0, 1.0, 0.0, 0.0, 0.0, 1.0, 0.0, 1.0, 0.0], [1.0, 0.0, 0.0, 1.0, 1.0, 0.0, 1.0, 0.0, 1.0, 0.0, 0.0, 1.0, 0.0, 0.0, 1.0, 0.0, 0.0, 0.0, 0.0, 0.0, 0.0, 0.0, 0.0, 0.0], [1.0, 0.0, 1.0, 0.0, 0.0, 0.0, 0.0, 0.0, 1.0, 0.0, 1.0, 0.0, NaN, NaN, NaN, NaN, NaN, NaN, NaN, NaN, NaN, NaN, NaN, NaN], [0.0, 0.0, 1.0, 1.0, 0.0, 0.0, 0.0, 1.0, 1.0, 0.0, 1.0, 1.0, NaN, NaN, NaN, NaN, NaN, NaN, NaN, NaN, NaN, NaN, NaN, NaN]], "ffr_recalled": [[0.0, 0.0, 0.0, 0.0, 0.0, 0.0, 0.0, 0.0, 0.0, 0.0, 0.0, 0.0, 0.0, 0.0, 0.0, 0.0, 0.0, 0.0, NaN, NaN, NaN, NaN, NaN, NaN], [0.0, 0.0, 0.0, 0.0, 0.0, 0.0, 0.0, 0.0, 0.0, 0.0, 0.0, 0.0, 0.0, 0.0, 0.0, 0.0, 0.0, 0.0, NaN, NaN, NaN, NaN, NaN, NaN], [0.0, 0.0, 0.0, 0.0, 0.0, 0.0, 0.0, 0.0, 0.0, 0.0, 0.0, 0.0, NaN, NaN, NaN, NaN, NaN, NaN, NaN, NaN, NaN, NaN, NaN, NaN], [0.0, 0.0, 0.0, 0.0, 1.0, 0.0, 0.0, 0.0, 0.0, 0.0, 0.0, 0.0, NaN, NaN, NaN, NaN, NaN, NaN, NaN, NaN, NaN, NaN, NaN, NaN], [0.0, 0.0, 0.0, 0.0, 0.0, 0.0, 0.0, 0.0, 0.0, 0.0, 0.0, 0.0, NaN, NaN, NaN, NaN, NaN, NaN, NaN, NaN, NaN, NaN, NaN, NaN], [0.0, 0.0, 0.0, 1.0, 0.0, 0.0, 0.0, 0.0, 0.0, 0.0, 0.0, 0.0, 0.0, 0.0, 0.0, 0.0, 0.0, 0.0, 0.0, 0.0, 0.0, 0.0, 0.0, 0.0], [0.0, 1.0, 0.0, 0.0, 0.0, 0.0, 0.0, 0.0, 0.0, 0.0, 0.0, 1.0, 0.0, 0.0, 0.0, 0.0, 0.0, 0.0, 0.0, 0.0, 0.0, 0.0, 0.0, 0.0], [0.0, 0.0, 0.0, 0.0, 0.0, 0.0, 1.0, 0.0, 0.0, 0.0, 0.0, 1.0, NaN, NaN, NaN, NaN, NaN, NaN, NaN, NaN, NaN, NaN, NaN, NaN], [0.0, 0.0, 1.0, 0.0, 0.0, 0.0, 0.0, 0.0, 0.0, 0.0, 0.0, 1.0, 0.0, 0.0, 0.0, 0.0, 0.0, 0.0, 0.0, 0.0, 0.0, 0.0, 0.0, 0.0], [1.0, 1.0, 0.0, 0.0, 1.0, 0.0, 0.0, 0.0, 0.0, 0.0, 0.0, 0.0, NaN, NaN, NaN, NaN, NaN, NaN, NaN, NaN, NaN, NaN, NaN, NaN], [0.0, 0.0, 0.0, 1.0, 0.0, 0.0, 0.0, 0.0, 0.0, 1.0, 0.0, 0.0, NaN, NaN, NaN, NaN, NaN, NaN, NaN, NaN, NaN, NaN, NaN, NaN], [0.0, 0.0, 0.0, 0.0, 0.0, 0.0, 0.0, 0.0, 0.0, 0.0, 0.0, 0.0, 0.0, 0.0, 0.0, 0.0, 0.0, 0.0, 0.0, 0.0, 1.0, 0.0, 0.0, 0.0], [0.0, 0.0, 0.0, 0.0, 0.0, 1.0, 0.0, 0.0, 0.0, 0.0, 0.0, 0.0, 0.0, 0.0, 0.0, 0.0, 0.0, 0.0, 0.0, 0.0, 0.0, 0.0, 0.0, 0.0], [0.0, 0.0, 0.0, 0.0, 0.0, 0.0, 1.0, 0.0, 0.0, 0.0, 0.0, 0.0, 0.0, 0.0, 0.0, 0.0, 0.0, 0.0, 0.0, 0.0, 0.0, 0.0, 0.0, 0.0], [0.0, 0.0, 0.0, 0.0, 0.0, 1.0, 0.0, 0.0, 0.0, 0.0, 0.0, 0.0, 0.0, 0.0, 0.0, 0.0, 0.0, 0.0, 0.0, 0.0, 1.0, 0.0, 0.0, 0.0], [0.0, 0.0, 0.0, 1.0, 0.0, 0.0, 0.0, 0.0, 0.0, 0.0, 0.0, 0.0, 0.0, 0.0, 1.0, 0.0, 0.0, 0.0, 0.0, 0.0, 0.0, 0.0, 0.0, 0.0], [0.0, 0.0, 0.0, 0.0, 0.0, 0.0, 0.0, 0.0, 1.0, 0.0, 0.0, 0.0, NaN, NaN, NaN, NaN, NaN, NaN, NaN, NaN, NaN, NaN, NaN, NaN], [0.0, 0.0, 1.0, 1.0, 1.0, 0.0, 0.0, 0.0, 0.0, 0.0, 0.0, 0.0, NaN, NaN, NaN, NaN, NaN, NaN, NaN, NaN, NaN, NaN, NaN, NaN]], "ffr_rt": [7959, 16738, 31888, 36197, 44199, 51384, 58678, 67668, 73886, 82088, 90786, 100022, 109624, 118720, 125109, 136575, 145875, 153411, 160851, 173861, 180330, 192468, 208537, 217471, 231278, 244797, 252530, 261885, 268207, 273329], "subject": ["MTK3194", "MTK3194", "MTK3194", "MTK3194", "MTK3194", "MTK3194", "MTK3194", "MTK3194", "MTK3194", "MTK3194", "MTK3194", "MTK3194", "MTK3194", "MTK3194", "MTK3194", "MTK3194", "MTK3194", "MTK3194"], "intrusions": [[0, 0, 0, 0, 0, -1, 0, 0, 0, 0, 0, 0], [0, -1, 1, 0, 0, 0, 0, 0, 0, 0, 0, 0], [-1, -1, 0, -1, 0, -1, -1, 0, 0, 0, 0, 0], [-1, 0, 0, 0, 0, 0, 0, -1, 0, 0, 0, 0], [0, 0, -1, 0, 0, 0, 0, 0, 0, 0, 0, 0], [0, 0, 0, 0, 0, -1, 0, -1, -1, 0, 0, -1], [0, 0, 0, 0, 0, 0, 0, 0, 0, 0, -1, -1], [-1, 0, 0, 0, 0, 0, 0, 0, 0, 0, -1, 0], [-1, 0, -1, -1, -1, 0, 0, -1, 2, 0, -1, 0], [0, 0, 0, 0, 0, 0, 0, 0, -1, 0, 0, 0], [0, 0, 0, 0, 0, -1, 0, 0, -1, 0, 0, 0], [-1, 0, -1, 0, 0, 0, 0, 0, 0, 0, 0, -1], [0, 0, 0, 8, 0, 0, 1, 0, -1, 0, 0, 0], [0, 0, 0, 0, 0, 0, 0, 0, -1, 0, 0, 0], [-1, 0, 0, 0, 0, 0, 0, 0, 0, 0, 0, 0], [0, 0, 0, 0, 0, -1, 0, 0, 0, 0, 0, 0], [0, 0, -1, 0, 0, 0, 0, 0, 0, 0, 0, 0], [-1, 0, 0, 0, 0, -1, 0, 0, 0, 0, 0, 0]]}